oneapi/__init__.py
oneapi/api_requestor.py
oneapi/api_resources/__init__.py
oneapi/api_resources/movie.py
oneapi/api_resources/quote.py
oneapi/api_resources/utils.py
oneapi/api_resources/abstract/api_resource.py
oneapi/api_resources/abstract/listable_api_resource.py
oneapi/api_resources/abstract/retrievable_api_resource.py
oneapi_sdk-0.0.4.dist-info/METADATA
oneapi_sdk-0.0.4.dist-info/WHEEL
oneapi_sdk-0.0.4.dist-info/licenses/LICENSE
oneapi_sdk-0.0.4.dist-info/RECORD
