Metadata-Version: 2.1
Name: oneapi-sdk
Version: 0.0.4
Summary: A Python SDK for The One API
Author-email: Eduardo Felipe Weber <eduardo-felipe-weber@hotmail.com>
License-File: LICENSE
Classifier: License :: OSI Approved :: MIT License
Classifier: Operating System :: OS Independent
Classifier: Programming Language :: Python :: 3
Requires-Python: >=3.9.0
Requires-Dist: certifi==2023.5.7
Requires-Dist: charset-normalizer==3.1.0
Requires-Dist: exceptiongroup==1.1.1
Requires-Dist: idna==3.4
Requires-Dist: iniconfig==2.0.0
Requires-Dist: mock==5.0.2
Requires-Dist: packaging==23.1
Requires-Dist: pluggy==1.0.0
Requires-Dist: pytest==7.3.2
Requires-Dist: requests==2.31.0
Requires-Dist: tomli==2.0.1
Requires-Dist: urllib3==2.0.3
